{
  "$schema": "https://raw.githubusercontent.com/YosysHQ/yosys/main/misc/jny.schema.json",
  "generator": "Yosys 0.63 (git sha1 70a11c6bf0e8dd669f56c7da3587f78b405138e2, clang++ 17.0.0 -fPIC -O3)",
  "version": "0.0.1",
  "invocation": "write_jny -no-connections ../model/design.json ",
  "features": ["attributes", "properties"],
  "modules": [
      {
        "name": "top",
        "cell_sorts": [
          {
            "type": "$mux",
            "ports": [
                {
                  "name": "A",
                  "direction": "io",
                  "range": [0, 0]
                },
                {
                  "name": "B",
                  "direction": "io",
                  "range": [0, 0]
                },
                {
                  "name": "S",
                  "direction": "io",
                  "range": [0, 0]
                },
                {
                  "name": "Y",
                  "direction": "",
                  "range": [0, 0]
                }
            ],
            "cells": [
                {
                  "name": "$procmux$148",
                  "attributes": {
                    "src": "dut_temp.sv:287.9-287.108|dut_temp.sv:287.5-288.68"
                  },
                  "parameters": {
                    "WIDTH": "00000000000000000000000000000001"
                  }
                },
                {
                  "name": "$procmux$150",
                  "attributes": {
                    "src": "dut_temp.sv:217.17-217.37|dut_temp.sv:217.13-217.52"
                  },
                  "parameters": {
                    "WIDTH": "00000000000000000000000000000001"
                  }
                },
                {
                  "name": "$procmux$152",
                  "attributes": {
                    "src": "dut_temp.sv:216.27-216.47|dut_temp.sv:216.23-216.84"
                  },
                  "parameters": {
                    "WIDTH": "00000000000000000000000000000010"
                  }
                },
                {
                  "name": "$procmux$171",
                  "attributes": {
                    "full_case": "00000000000000000000000000000001",
                    "src": "dut_temp.sv:188.16-188.31|dut_temp.sv:188.13-204.16"
                  },
                  "parameters": {
                    "WIDTH": "00000000000000000000000000000011"
                  }
                },
                {
                  "name": "$procmux$205",
                  "attributes": {
                    "full_case": "00000000000000000000000000000001",
                    "src": "dut_temp.sv:168.16-168.31|dut_temp.sv:168.13-184.16"
                  },
                  "parameters": {
                    "WIDTH": "00000000000000000000000000000011"
                  }
                },
                {
                  "name": "$procmux$211",
                  "attributes": {
                    "full_case": "00000000000000000000000000000001",
                    "src": "dut_temp.sv:168.16-168.31|dut_temp.sv:168.13-184.16"
                  },
                  "parameters": {
                    "WIDTH": "00000000000000000000000000000001"
                  }
                },
                {
                  "name": "$procmux$244",
                  "attributes": {
                    "full_case": "00000000000000000000000000000001",
                    "src": "dut_temp.sv:148.16-148.31|dut_temp.sv:148.13-164.16"
                  },
                  "parameters": {
                    "WIDTH": "00000000000000000000000000000011"
                  }
                },
                {
                  "name": "$procmux$288",
                  "attributes": {
                    "full_case": "00000000000000000000000000000001",
                    "src": "dut_temp.sv:128.16-128.31|dut_temp.sv:128.13-144.16"
                  },
                  "parameters": {
                    "WIDTH": "00000000000000000000000000000011"
                  }
                },
                {
                  "name": "$procmux$337",
                  "attributes": {
                    "full_case": "00000000000000000000000000000001",
                    "src": "dut_temp.sv:108.16-108.31|dut_temp.sv:108.13-124.16"
                  },
                  "parameters": {
                    "WIDTH": "00000000000000000000000000000011"
                  }
                },
                {
                  "name": "$procmux$391",
                  "attributes": {
                    "full_case": "00000000000000000000000000000001",
                    "src": "dut_temp.sv:88.16-88.31|dut_temp.sv:88.13-104.16"
                  },
                  "parameters": {
                    "WIDTH": "00000000000000000000000000000011"
                  }
                },
                {
                  "name": "$procmux$450",
                  "attributes": {
                    "full_case": "00000000000000000000000000000001",
                    "src": "dut_temp.sv:68.16-68.31|dut_temp.sv:68.13-84.15"
                  },
                  "parameters": {
                    "WIDTH": "00000000000000000000000000000011"
                  }
                },
                {
                  "name": "$procmux$514",
                  "attributes": {
                    "full_case": "00000000000000000000000000000001",
                    "src": "dut_temp.sv:48.16-48.31|dut_temp.sv:48.13-64.15"
                  },
                  "parameters": {
                    "WIDTH": "00000000000000000000000000000011"
                  }
                },
                {
                  "name": "$procmux$551",
                  "attributes": {
                    "full_case": "00000000000000000000000000000001",
                    "src": "dut_temp.sv:185.13-185.13|dut_temp.sv:45.7-206.14"
                  },
                  "parameters": {
                    "WIDTH": "00000000000000000000000000000001"
                  }
                },
                {
                  "name": "$procmux$570",
                  "attributes": {
                    "full_case": "00000000000000000000000000000001",
                    "src": "dut_temp.sv:38.15-38.53|dut_temp.sv:38.12-41.29"
                  },
                  "parameters": {
                    "WIDTH": "00000000000000000000000000000011"
                  }
                },
                {
                  "name": "$procmux$573",
                  "attributes": {
                    "full_case": "00000000000000000000000000000001",
                    "src": "dut_temp.sv:36.15-36.27|dut_temp.sv:36.12-41.29"
                  },
                  "parameters": {
                    "WIDTH": "00000000000000000000000000000011"
                  }
                }
            ]
          },
          {
            "type": "$lt",
            "ports": [
                {
                  "name": "A",
                  "direction": "io",
                  "range": [2, 0]
                },
                {
                  "name": "B",
                  "direction": "io",
                  "range": [2, 0]
                },
                {
                  "name": "Y",
                  "direction": "",
                  "range": [0, 0]
                }
            ],
            "cells": [
                {
                  "name": "$lt$dut_temp.sv:216$49",
                  "attributes": {
                    "src": "dut_temp.sv:216.27-216.47"
                  },
                  "parameters": {
                    "A_SIGNED": "00000000000000000000000000000000",
                    "A_WIDTH": "00000000000000000000000000000010",
                    "B_SIGNED": "00000000000000000000000000000000",
                    "B_WIDTH": "00000000000000000000000000000010",
                    "Y_WIDTH": "00000000000000000000000000000001"
                  }
                },
                {
                  "name": "$lt$dut_temp.sv:217$52",
                  "attributes": {
                    "src": "dut_temp.sv:217.17-217.37"
                  },
                  "parameters": {
                    "A_SIGNED": "00000000000000000000000000000000",
                    "A_WIDTH": "00000000000000000000000000000010",
                    "B_SIGNED": "00000000000000000000000000000000",
                    "B_WIDTH": "00000000000000000000000000000010",
                    "Y_WIDTH": "00000000000000000000000000000001"
                  }
                }
            ]
          },
          {
            "type": "$adff",
            "ports": [
                {
                  "name": "ARST",
                  "direction": "io",
                  "range": [0, 0]
                },
                {
                  "name": "CLK",
                  "direction": "io",
                  "range": [0, 0]
                },
                {
                  "name": "D",
                  "direction": "io",
                  "range": [3, 0]
                },
                {
                  "name": "Q",
                  "direction": "",
                  "range": [3, 0]
                }
            ],
            "cells": [
                {
                  "name": "$procdff$744",
                  "attributes": {
                    "src": "dut_temp.sv:32.4-42.7"
                  },
                  "parameters": {
                    "ARST_POLARITY": "00000000000000000000000000000000",
                    "ARST_VALUE": "000",
                    "CLK_POLARITY": "1",
                    "WIDTH": "00000000000000000000000000000011"
                  }
                }
            ]
          },
          {
            "type": "$check",
            "ports": [
                {
                  "name": "A",
                  "direction": "io",
                  "range": [0, 0]
                },
                {
                  "name": "ARGS",
                  "direction": "io",
                  "range": [0, 0]
                },
                {
                  "name": "EN",
                  "direction": "io",
                  "range": [0, 0]
                },
                {
                  "name": "TRG",
                  "direction": "io",
                  "range": [0, 0]
                }
            ],
            "cells": [
                {
                  "name": "_witness_.check_assume_dut_temp_sv_217_53",
                  "attributes": {
                    "hdlname": "_witness_ check_assume_dut_temp_sv_217_53",
                    "keep": "00000000000000000000000000000001",
                    "src": "dut_temp.sv:217.39-217.51"
                  },
                  "parameters": {
                    "ARGS_WIDTH": "00000000000000000000000000000000",
                    "FLAVOR": "assume",
                    "FORMAT": true,
                    "PRIORITY": "11111111111111111111111111111111",
                    "TRG_ENABLE": "00000000000000000000000000000000",
                    "TRG_POLARITY": true,
                    "TRG_WIDTH": "00000000000000000000000000000000"
                  }
                },
                {
                  "name": "a_nstate_trans_001_to_010_r4_alt",
                  "attributes": {
                    "keep": "00000000000000000000000000000001",
                    "src": "dut_temp.sv:288.9-288.67"
                  },
                  "parameters": {
                    "ARGS_WIDTH": "00000000000000000000000000000000",
                    "FLAVOR": "assert",
                    "FORMAT": true,
                    "PRIORITY": "11111111111111111111111111111111",
                    "TRG_ENABLE": "00000000000000000000000000000001",
                    "TRG_POLARITY": "1",
                    "TRG_WIDTH": "00000000000000000000000000000001"
                  }
                }
            ]
          },
          {
            "type": "$pmux",
            "ports": [
                {
                  "name": "A",
                  "direction": "io",
                  "range": [3, 0]
                },
                {
                  "name": "B",
                  "direction": "io",
                  "range": [6, 0]
                },
                {
                  "name": "S",
                  "direction": "io",
                  "range": [2, 0]
                },
                {
                  "name": "Y",
                  "direction": "",
                  "range": [3, 0]
                }
            ],
            "cells": [
                {
                  "name": "$procmux$154",
                  "attributes": {
                    "full_case": "00000000000000000000000000000001",
                    "src": "dut_temp.sv:201.44-201.44|dut_temp.sv:200.16-203.23"
                  },
                  "parameters": {
                    "S_WIDTH": "00000000000000000000000000000010",
                    "WIDTH": "00000000000000000000000000000011"
                  }
                },
                {
                  "name": "$procmux$163",
                  "attributes": {
                    "full_case": "00000000000000000000000000000001",
                    "src": "dut_temp.sv:192.44-192.44|dut_temp.sv:191.16-194.23"
                  },
                  "parameters": {
                    "S_WIDTH": "00000000000000000000000000000010",
                    "WIDTH": "00000000000000000000000000000011"
                  }
                },
                {
                  "name": "$procmux$186",
                  "attributes": {
                    "full_case": "00000000000000000000000000000001",
                    "src": "dut_temp.sv:181.44-181.44|dut_temp.sv:180.16-183.23"
                  },
                  "parameters": {
                    "S_WIDTH": "00000000000000000000000000000010",
                    "WIDTH": "00000000000000000000000000000011"
                  }
                },
                {
                  "name": "$procmux$196",
                  "attributes": {
                    "full_case": "00000000000000000000000000000001",
                    "src": "dut_temp.sv:172.44-172.44|dut_temp.sv:171.16-174.23"
                  },
                  "parameters": {
                    "S_WIDTH": "00000000000000000000000000000010",
                    "WIDTH": "00000000000000000000000000000011"
                  }
                },
                {
                  "name": "$procmux$223",
                  "attributes": {
                    "full_case": "00000000000000000000000000000001",
                    "src": "dut_temp.sv:161.44-161.44|dut_temp.sv:160.16-163.23"
                  },
                  "parameters": {
                    "S_WIDTH": "00000000000000000000000000000010",
                    "WIDTH": "00000000000000000000000000000011"
                  }
                },
                {
                  "name": "$procmux$234",
                  "attributes": {
                    "full_case": "00000000000000000000000000000001",
                    "src": "dut_temp.sv:152.44-152.44|dut_temp.sv:151.16-154.23"
                  },
                  "parameters": {
                    "S_WIDTH": "00000000000000000000000000000010",
                    "WIDTH": "00000000000000000000000000000011"
                  }
                },
                {
                  "name": "$procmux$265",
                  "attributes": {
                    "full_case": "00000000000000000000000000000001",
                    "src": "dut_temp.sv:141.44-141.44|dut_temp.sv:140.16-143.23"
                  },
                  "parameters": {
                    "S_WIDTH": "00000000000000000000000000000010",
                    "WIDTH": "00000000000000000000000000000011"
                  }
                },
                {
                  "name": "$procmux$277",
                  "attributes": {
                    "full_case": "00000000000000000000000000000001",
                    "src": "dut_temp.sv:132.44-132.44|dut_temp.sv:131.16-134.23"
                  },
                  "parameters": {
                    "S_WIDTH": "00000000000000000000000000000010",
                    "WIDTH": "00000000000000000000000000000011"
                  }
                },
                {
                  "name": "$procmux$312",
                  "attributes": {
                    "full_case": "00000000000000000000000000000001",
                    "src": "dut_temp.sv:121.44-121.44|dut_temp.sv:120.16-123.23"
                  },
                  "parameters": {
                    "S_WIDTH": "00000000000000000000000000000010",
                    "WIDTH": "00000000000000000000000000000011"
                  }
                },
                {
                  "name": "$procmux$325",
                  "attributes": {
                    "full_case": "00000000000000000000000000000001",
                    "src": "dut_temp.sv:112.44-112.44|dut_temp.sv:111.16-114.23"
                  },
                  "parameters": {
                    "S_WIDTH": "00000000000000000000000000000010",
                    "WIDTH": "00000000000000000000000000000011"
                  }
                },
                {
                  "name": "$procmux$364",
                  "attributes": {
                    "full_case": "00000000000000000000000000000001",
                    "src": "dut_temp.sv:101.44-101.44|dut_temp.sv:100.16-103.23"
                  },
                  "parameters": {
                    "S_WIDTH": "00000000000000000000000000000010",
                    "WIDTH": "00000000000000000000000000000011"
                  }
                },
                {
                  "name": "$procmux$378",
                  "attributes": {
                    "full_case": "00000000000000000000000000000001",
                    "src": "dut_temp.sv:92.44-92.44|dut_temp.sv:91.16-94.23"
                  },
                  "parameters": {
                    "S_WIDTH": "00000000000000000000000000000010",
                    "WIDTH": "00000000000000000000000000000011"
                  }
                },
                {
                  "name": "$procmux$421",
                  "attributes": {
                    "full_case": "00000000000000000000000000000001",
                    "src": "dut_temp.sv:81.44-81.44|dut_temp.sv:80.16-83.23"
                  },
                  "parameters": {
                    "S_WIDTH": "00000000000000000000000000000010",
                    "WIDTH": "00000000000000000000000000000011"
                  }
                },
                {
                  "name": "$procmux$436",
                  "attributes": {
                    "full_case": "00000000000000000000000000000001",
                    "src": "dut_temp.sv:72.44-72.44|dut_temp.sv:71.16-74.23"
                  },
                  "parameters": {
                    "S_WIDTH": "00000000000000000000000000000010",
                    "WIDTH": "00000000000000000000000000000011"
                  }
                },
                {
                  "name": "$procmux$483",
                  "attributes": {
                    "full_case": "00000000000000000000000000000001",
                    "src": "dut_temp.sv:61.44-61.44|dut_temp.sv:60.16-63.23"
                  },
                  "parameters": {
                    "S_WIDTH": "00000000000000000000000000000010",
                    "WIDTH": "00000000000000000000000000000011"
                  }
                },
                {
                  "name": "$procmux$499",
                  "attributes": {
                    "full_case": "00000000000000000000000000000001",
                    "src": "dut_temp.sv:52.44-52.44|dut_temp.sv:51.16-54.23"
                  },
                  "parameters": {
                    "S_WIDTH": "00000000000000000000000000000010",
                    "WIDTH": "00000000000000000000000000000011"
                  }
                },
                {
                  "name": "$procmux$542",
                  "attributes": {
                    "full_case": "00000000000000000000000000000001",
                    "src": "dut_temp.sv:185.13-185.13|dut_temp.sv:45.7-206.14"
                  },
                  "parameters": {
                    "S_WIDTH": "00000000000000000000000000001000",
                    "WIDTH": "00000000000000000000000000000011"
                  }
                },
                {
                  "name": "$procmux$560",
                  "attributes": {
                    "full_case": "00000000000000000000000000000001",
                    "src": "dut_temp.sv:185.13-185.13|dut_temp.sv:45.7-206.14"
                  },
                  "parameters": {
                    "S_WIDTH": "00000000000000000000000000000111",
                    "WIDTH": "00000000000000000000000000000001"
                  }
                }
            ]
          },
          {
            "type": "$dff",
            "ports": [
                {
                  "name": "CLK",
                  "direction": "io",
                  "range": [0, 0]
                },
                {
                  "name": "D",
                  "direction": "io",
                  "range": [0, 0]
                },
                {
                  "name": "Q",
                  "direction": "",
                  "range": [0, 0]
                }
            ],
            "cells": [
                {
                  "name": "$procdff$708",
                  "attributes": {
                    "src": "dut_temp.sv:286.1-289.4"
                  },
                  "parameters": {
                    "CLK_POLARITY": "1",
                    "WIDTH": "00000000000000000000000000000001"
                  }
                },
                {
                  "name": "$procdff$709",
                  "attributes": {
                    "src": "dut_temp.sv:286.1-289.4"
                  },
                  "parameters": {
                    "CLK_POLARITY": "1",
                    "WIDTH": "00000000000000000000000000000001"
                  }
                },
                {
                  "name": "$procdff$710",
                  "attributes": {
                    "src": "dut_temp.sv:286.1-289.4"
                  },
                  "parameters": {
                    "CLK_POLARITY": "1",
                    "WIDTH": "00000000000000000000000000000011"
                  }
                },
                {
                  "name": "$procdff$711",
                  "attributes": {
                    "src": "dut_temp.sv:286.1-289.4"
                  },
                  "parameters": {
                    "CLK_POLARITY": "1",
                    "WIDTH": "00000000000000000000000000000001"
                  }
                },
                {
                  "name": "$procdff$738",
                  "attributes": {
                    "src": "dut_temp.sv:216.1-216.84"
                  },
                  "parameters": {
                    "CLK_POLARITY": "1",
                    "WIDTH": "00000000000000000000000000000010"
                  }
                },
                {
                  "name": "$procdff$739",
                  "attributes": {
                    "src": "dut_temp.sv:213.1-213.41"
                  },
                  "parameters": {
                    "CLK_POLARITY": "1",
                    "WIDTH": "00000000000000000000000000000001"
                  }
                },
                {
                  "name": "$procdff$745",
                  "attributes": {
                    "src": "dut_temp.sv:26.4-31.7"
                  },
                  "parameters": {
                    "CLK_POLARITY": "1",
                    "WIDTH": "00000000000000000000000000000001"
                  }
                },
                {
                  "name": "$procdff$746",
                  "attributes": {
                    "src": "dut_temp.sv:26.4-31.7"
                  },
                  "parameters": {
                    "CLK_POLARITY": "1",
                    "WIDTH": "00000000000000000000000000000001"
                  }
                },
                {
                  "name": "$procdff$747",
                  "attributes": {
                    "src": "dut_temp.sv:26.4-31.7"
                  },
                  "parameters": {
                    "CLK_POLARITY": "1",
                    "WIDTH": "00000000000000000000000000000001"
                  }
                }
            ]
          },
          {
            "type": "$logic_not",
            "ports": [
                {
                  "name": "A",
                  "direction": "io",
                  "range": [0, 0]
                },
                {
                  "name": "Y",
                  "direction": "",
                  "range": [0, 0]
                }
            ],
            "cells": [
                {
                  "name": "$logic_not$dut_temp.sv:217$54",
                  "attributes": {
                    "src": "dut_temp.sv:217.46-217.50"
                  },
                  "parameters": {
                    "A_SIGNED": "00000000000000000000000000000000",
                    "A_WIDTH": "00000000000000000000000000000001",
                    "Y_WIDTH": "00000000000000000000000000000001"
                  }
                },
                {
                  "name": "$logic_not$dut_temp.sv:287$138",
                  "attributes": {
                    "src": "dut_temp.sv:287.25-287.36"
                  },
                  "parameters": {
                    "A_SIGNED": "00000000000000000000000000000000",
                    "A_WIDTH": "00000000000000000000000000000001",
                    "Y_WIDTH": "00000000000000000000000000000001"
                  }
                },
                {
                  "name": "$procmux$517_CMP0",
                  "attributes": {
                    "full_case": "00000000000000000000000000000001",
                    "src": "dut_temp.sv:45.20-45.20|dut_temp.sv:45.7-206.14"
                  },
                  "parameters": {
                    "A_SIGNED": "00000000000000000000000000000000",
                    "A_WIDTH": "00000000000000000000000000000011",
                    "Y_WIDTH": "00000000000000000000000000000001"
                  }
                }
            ]
          },
          {
            "type": "$logic_and",
            "ports": [
                {
                  "name": "A",
                  "direction": "io",
                  "range": [0, 0]
                },
                {
                  "name": "B",
                  "direction": "io",
                  "range": [0, 0]
                },
                {
                  "name": "Y",
                  "direction": "",
                  "range": [0, 0]
                }
            ],
            "cells": [
                {
                  "name": "$logic_and$dut_temp.sv:287$139",
                  "attributes": {
                    "src": "dut_temp.sv:287.9-287.36"
                  },
                  "parameters": {
                    "A_SIGNED": "00000000000000000000000000000000",
                    "A_WIDTH": "00000000000000000000000000000001",
                    "B_SIGNED": "00000000000000000000000000000000",
                    "B_WIDTH": "00000000000000000000000000000001",
                    "Y_WIDTH": "00000000000000000000000000000001"
                  }
                },
                {
                  "name": "$logic_and$dut_temp.sv:287$140",
                  "attributes": {
                    "src": "dut_temp.sv:287.9-287.53"
                  },
                  "parameters": {
                    "A_SIGNED": "00000000000000000000000000000000",
                    "A_WIDTH": "00000000000000000000000000000001",
                    "B_SIGNED": "00000000000000000000000000000000",
                    "B_WIDTH": "00000000000000000000000000000001",
                    "Y_WIDTH": "00000000000000000000000000000001"
                  }
                },
                {
                  "name": "$logic_and$dut_temp.sv:287$142",
                  "attributes": {
                    "src": "dut_temp.sv:287.9-287.80"
                  },
                  "parameters": {
                    "A_SIGNED": "00000000000000000000000000000000",
                    "A_WIDTH": "00000000000000000000000000000001",
                    "B_SIGNED": "00000000000000000000000000000000",
                    "B_WIDTH": "00000000000000000000000000000001",
                    "Y_WIDTH": "00000000000000000000000000000001"
                  }
                },
                {
                  "name": "$logic_and$dut_temp.sv:287$144",
                  "attributes": {
                    "src": "dut_temp.sv:287.9-287.108"
                  },
                  "parameters": {
                    "A_SIGNED": "00000000000000000000000000000000",
                    "A_WIDTH": "00000000000000000000000000000001",
                    "B_SIGNED": "00000000000000000000000000000000",
                    "B_WIDTH": "00000000000000000000000000000001",
                    "Y_WIDTH": "00000000000000000000000000000001"
                  }
                },
                {
                  "name": "$logic_and$dut_temp.sv:38$37",
                  "attributes": {
                    "src": "dut_temp.sv:38.15-38.53"
                  },
                  "parameters": {
                    "A_SIGNED": "00000000000000000000000000000000",
                    "A_WIDTH": "00000000000000000000000000000001",
                    "B_SIGNED": "00000000000000000000000000000000",
                    "B_WIDTH": "00000000000000000000000000000001",
                    "Y_WIDTH": "00000000000000000000000000000001"
                  }
                }
            ]
          },
          {
            "type": "$eq",
            "ports": [
                {
                  "name": "A",
                  "direction": "io",
                  "range": [3, 0]
                },
                {
                  "name": "B",
                  "direction": "io",
                  "range": [0, 0]
                },
                {
                  "name": "Y",
                  "direction": "",
                  "range": [0, 0]
                }
            ],
            "cells": [
                {
                  "name": "$eq$dut_temp.sv:287$141",
                  "attributes": {
                    "src": "dut_temp.sv:287.57-287.80"
                  },
                  "parameters": {
                    "A_SIGNED": "00000000000000000000000000000000",
                    "A_WIDTH": "00000000000000000000000000000011",
                    "B_SIGNED": "00000000000000000000000000000000",
                    "B_WIDTH": "00000000000000000000000000000001",
                    "Y_WIDTH": "00000000000000000000000000000001"
                  }
                },
                {
                  "name": "$eq$dut_temp.sv:288$145",
                  "attributes": {
                    "src": "dut_temp.sv:288.50-288.66"
                  },
                  "parameters": {
                    "A_SIGNED": "00000000000000000000000000000000",
                    "A_WIDTH": "00000000000000000000000000000011",
                    "B_SIGNED": "00000000000000000000000000000000",
                    "B_WIDTH": "00000000000000000000000000000010",
                    "Y_WIDTH": "00000000000000000000000000000001"
                  }
                },
                {
                  "name": "$procmux$307_CMP0",
                  "attributes": {
                    "full_case": "00000000000000000000000000000001",
                    "src": "dut_temp.sv:125.13-125.13|dut_temp.sv:45.7-206.14"
                  },
                  "parameters": {
                    "A_SIGNED": "00000000000000000000000000000000",
                    "A_WIDTH": "00000000000000000000000000000011",
                    "B_SIGNED": "00000000000000000000000000000000",
                    "B_WIDTH": "00000000000000000000000000000011",
                    "Y_WIDTH": "00000000000000000000000000000001"
                  }
                },
                {
                  "name": "$procmux$358_CMP0",
                  "attributes": {
                    "full_case": "00000000000000000000000000000001",
                    "src": "dut_temp.sv:105.13-105.13|dut_temp.sv:45.7-206.14"
                  },
                  "parameters": {
                    "A_SIGNED": "00000000000000000000000000000000",
                    "A_WIDTH": "00000000000000000000000000000011",
                    "B_SIGNED": "00000000000000000000000000000000",
                    "B_WIDTH": "00000000000000000000000000000010",
                    "Y_WIDTH": "00000000000000000000000000000001"
                  }
                },
                {
                  "name": "$procmux$414_CMP0",
                  "attributes": {
                    "full_case": "00000000000000000000000000000001",
                    "src": "dut_temp.sv:85.13-85.13|dut_temp.sv:45.7-206.14"
                  },
                  "parameters": {
                    "A_SIGNED": "00000000000000000000000000000000",
                    "A_WIDTH": "00000000000000000000000000000011",
                    "B_SIGNED": "00000000000000000000000000000000",
                    "B_WIDTH": "00000000000000000000000000000010",
                    "Y_WIDTH": "00000000000000000000000000000001"
                  }
                },
                {
                  "name": "$procmux$475_CMP0",
                  "attributes": {
                    "full_case": "00000000000000000000000000000001",
                    "src": "dut_temp.sv:65.13-65.13|dut_temp.sv:45.7-206.14"
                  },
                  "parameters": {
                    "A_SIGNED": "00000000000000000000000000000000",
                    "A_WIDTH": "00000000000000000000000000000011",
                    "B_SIGNED": "00000000000000000000000000000000",
                    "B_WIDTH": "00000000000000000000000000000001",
                    "Y_WIDTH": "00000000000000000000000000000001"
                  }
                },
                {
                  "name": "$procmux$544_CMP0",
                  "attributes": {
                    "full_case": "00000000000000000000000000000001",
                    "src": "dut_temp.sv:165.13-165.13|dut_temp.sv:45.7-206.14"
                  },
                  "parameters": {
                    "A_SIGNED": "00000000000000000000000000000000",
                    "A_WIDTH": "00000000000000000000000000000011",
                    "B_SIGNED": "00000000000000000000000000000000",
                    "B_WIDTH": "00000000000000000000000000000011",
                    "Y_WIDTH": "00000000000000000000000000000001"
                  }
                },
                {
                  "name": "$procmux$545_CMP0",
                  "attributes": {
                    "full_case": "00000000000000000000000000000001",
                    "src": "dut_temp.sv:145.13-145.13|dut_temp.sv:45.7-206.14"
                  },
                  "parameters": {
                    "A_SIGNED": "00000000000000000000000000000000",
                    "A_WIDTH": "00000000000000000000000000000011",
                    "B_SIGNED": "00000000000000000000000000000000",
                    "B_WIDTH": "00000000000000000000000000000011",
                    "Y_WIDTH": "00000000000000000000000000000001"
                  }
                },
                {
                  "name": "$procmux$552_CMP0",
                  "attributes": {
                    "full_case": "00000000000000000000000000000001",
                    "src": "dut_temp.sv:185.13-185.13|dut_temp.sv:45.7-206.14"
                  },
                  "parameters": {
                    "A_SIGNED": "00000000000000000000000000000000",
                    "A_WIDTH": "00000000000000000000000000000011",
                    "B_SIGNED": "00000000000000000000000000000000",
                    "B_WIDTH": "00000000000000000000000000000011",
                    "Y_WIDTH": "00000000000000000000000000000001"
                  }
                }
            ]
          },
          {
            "type": "$not",
            "ports": [
                {
                  "name": "A",
                  "direction": "io",
                  "range": [0, 0]
                },
                {
                  "name": "Y",
                  "direction": "",
                  "range": [0, 0]
                }
            ],
            "cells": [
                {
                  "name": "$eq$dut_temp.sv:188$46",
                  "attributes": {
                    "src": "dut_temp.sv:188.16-188.31"
                  },
                  "parameters": {
                    "A_SIGNED": "00000000000000000000000000000000",
                    "A_WIDTH": "00000000000000000000000000000001",
                    "Y_WIDTH": "00000000000000000000000000000001"
                  }
                },
                {
                  "name": "$eq$dut_temp.sv:287$143",
                  "attributes": {
                    "src": "dut_temp.sv:287.84-287.108"
                  },
                  "parameters": {
                    "A_SIGNED": "00000000000000000000000000000000",
                    "A_WIDTH": "00000000000000000000000000000001",
                    "Y_WIDTH": "00000000000000000000000000000001"
                  }
                },
                {
                  "name": "$procmux$156_CMP0",
                  "attributes": {
                    "full_case": "00000000000000000000000000000001",
                    "src": "dut_temp.sv:200.31-200.31|dut_temp.sv:200.16-203.23"
                  },
                  "parameters": {
                    "A_SIGNED": "00000000000000000000000000000000",
                    "A_WIDTH": "00000000000000000000000000000001",
                    "Y_WIDTH": "00000000000000000000000000000001"
                  }
                },
                {
                  "name": "$procmux$165_CMP0",
                  "attributes": {
                    "full_case": "00000000000000000000000000000001",
                    "src": "dut_temp.sv:191.31-191.31|dut_temp.sv:191.16-194.23"
                  },
                  "parameters": {
                    "A_SIGNED": "00000000000000000000000000000000",
                    "A_WIDTH": "00000000000000000000000000000001",
                    "Y_WIDTH": "00000000000000000000000000000001"
                  }
                },
                {
                  "name": "$procmux$188_CMP0",
                  "attributes": {
                    "full_case": "00000000000000000000000000000001",
                    "src": "dut_temp.sv:180.31-180.31|dut_temp.sv:180.16-183.23"
                  },
                  "parameters": {
                    "A_SIGNED": "00000000000000000000000000000000",
                    "A_WIDTH": "00000000000000000000000000000001",
                    "Y_WIDTH": "00000000000000000000000000000001"
                  }
                },
                {
                  "name": "$procmux$198_CMP0",
                  "attributes": {
                    "full_case": "00000000000000000000000000000001",
                    "src": "dut_temp.sv:171.31-171.31|dut_temp.sv:171.16-174.23"
                  },
                  "parameters": {
                    "A_SIGNED": "00000000000000000000000000000000",
                    "A_WIDTH": "00000000000000000000000000000001",
                    "Y_WIDTH": "00000000000000000000000000000001"
                  }
                },
                {
                  "name": "$procmux$225_CMP0",
                  "attributes": {
                    "full_case": "00000000000000000000000000000001",
                    "src": "dut_temp.sv:160.31-160.31|dut_temp.sv:160.16-163.23"
                  },
                  "parameters": {
                    "A_SIGNED": "00000000000000000000000000000000",
                    "A_WIDTH": "00000000000000000000000000000001",
                    "Y_WIDTH": "00000000000000000000000000000001"
                  }
                },
                {
                  "name": "$procmux$236_CMP0",
                  "attributes": {
                    "full_case": "00000000000000000000000000000001",
                    "src": "dut_temp.sv:151.31-151.31|dut_temp.sv:151.16-154.23"
                  },
                  "parameters": {
                    "A_SIGNED": "00000000000000000000000000000000",
                    "A_WIDTH": "00000000000000000000000000000001",
                    "Y_WIDTH": "00000000000000000000000000000001"
                  }
                },
                {
                  "name": "$procmux$267_CMP0",
                  "attributes": {
                    "full_case": "00000000000000000000000000000001",
                    "src": "dut_temp.sv:140.31-140.31|dut_temp.sv:140.16-143.23"
                  },
                  "parameters": {
                    "A_SIGNED": "00000000000000000000000000000000",
                    "A_WIDTH": "00000000000000000000000000000001",
                    "Y_WIDTH": "00000000000000000000000000000001"
                  }
                },
                {
                  "name": "$procmux$279_CMP0",
                  "attributes": {
                    "full_case": "00000000000000000000000000000001",
                    "src": "dut_temp.sv:131.31-131.31|dut_temp.sv:131.16-134.23"
                  },
                  "parameters": {
                    "A_SIGNED": "00000000000000000000000000000000",
                    "A_WIDTH": "00000000000000000000000000000001",
                    "Y_WIDTH": "00000000000000000000000000000001"
                  }
                },
                {
                  "name": "$procmux$314_CMP0",
                  "attributes": {
                    "full_case": "00000000000000000000000000000001",
                    "src": "dut_temp.sv:120.31-120.31|dut_temp.sv:120.16-123.23"
                  },
                  "parameters": {
                    "A_SIGNED": "00000000000000000000000000000000",
                    "A_WIDTH": "00000000000000000000000000000001",
                    "Y_WIDTH": "00000000000000000000000000000001"
                  }
                },
                {
                  "name": "$procmux$327_CMP0",
                  "attributes": {
                    "full_case": "00000000000000000000000000000001",
                    "src": "dut_temp.sv:111.31-111.31|dut_temp.sv:111.16-114.23"
                  },
                  "parameters": {
                    "A_SIGNED": "00000000000000000000000000000000",
                    "A_WIDTH": "00000000000000000000000000000001",
                    "Y_WIDTH": "00000000000000000000000000000001"
                  }
                },
                {
                  "name": "$procmux$366_CMP0",
                  "attributes": {
                    "full_case": "00000000000000000000000000000001",
                    "src": "dut_temp.sv:100.31-100.31|dut_temp.sv:100.16-103.23"
                  },
                  "parameters": {
                    "A_SIGNED": "00000000000000000000000000000000",
                    "A_WIDTH": "00000000000000000000000000000001",
                    "Y_WIDTH": "00000000000000000000000000000001"
                  }
                },
                {
                  "name": "$procmux$380_CMP0",
                  "attributes": {
                    "full_case": "00000000000000000000000000000001",
                    "src": "dut_temp.sv:91.31-91.31|dut_temp.sv:91.16-94.23"
                  },
                  "parameters": {
                    "A_SIGNED": "00000000000000000000000000000000",
                    "A_WIDTH": "00000000000000000000000000000001",
                    "Y_WIDTH": "00000000000000000000000000000001"
                  }
                },
                {
                  "name": "$procmux$423_CMP0",
                  "attributes": {
                    "full_case": "00000000000000000000000000000001",
                    "src": "dut_temp.sv:80.31-80.31|dut_temp.sv:80.16-83.23"
                  },
                  "parameters": {
                    "A_SIGNED": "00000000000000000000000000000000",
                    "A_WIDTH": "00000000000000000000000000000001",
                    "Y_WIDTH": "00000000000000000000000000000001"
                  }
                },
                {
                  "name": "$procmux$438_CMP0",
                  "attributes": {
                    "full_case": "00000000000000000000000000000001",
                    "src": "dut_temp.sv:71.31-71.31|dut_temp.sv:71.16-74.23"
                  },
                  "parameters": {
                    "A_SIGNED": "00000000000000000000000000000000",
                    "A_WIDTH": "00000000000000000000000000000001",
                    "Y_WIDTH": "00000000000000000000000000000001"
                  }
                },
                {
                  "name": "$procmux$485_CMP0",
                  "attributes": {
                    "full_case": "00000000000000000000000000000001",
                    "src": "dut_temp.sv:60.31-60.31|dut_temp.sv:60.16-63.23"
                  },
                  "parameters": {
                    "A_SIGNED": "00000000000000000000000000000000",
                    "A_WIDTH": "00000000000000000000000000000001",
                    "Y_WIDTH": "00000000000000000000000000000001"
                  }
                },
                {
                  "name": "$procmux$501_CMP0",
                  "attributes": {
                    "full_case": "00000000000000000000000000000001",
                    "src": "dut_temp.sv:51.31-51.31|dut_temp.sv:51.16-54.23"
                  },
                  "parameters": {
                    "A_SIGNED": "00000000000000000000000000000000",
                    "A_WIDTH": "00000000000000000000000000000001",
                    "Y_WIDTH": "00000000000000000000000000000001"
                  }
                }
            ]
          },
          {
            "type": "$and",
            "ports": [
                {
                  "name": "A",
                  "direction": "io",
                  "range": [0, 0]
                },
                {
                  "name": "B",
                  "direction": "io",
                  "range": [0, 0]
                },
                {
                  "name": "Y",
                  "direction": "",
                  "range": [0, 0]
                }
            ],
            "cells": [
                {
                  "name": "$auto$proc_dlatch.cc:262:make_hold$585",
                  "attributes": {
                    "src": "dut_temp.sv:43.4-207.7"
                  },
                  "parameters": {
                    "A_SIGNED": "00000000000000000000000000000000",
                    "A_WIDTH": "00000000000000000000000000000001",
                    "B_SIGNED": "00000000000000000000000000000000",
                    "B_WIDTH": "00000000000000000000000000000001",
                    "Y_WIDTH": "00000000000000000000000000000001"
                  }
                },
                {
                  "name": "$auto$proc_dlatch.cc:262:make_hold$591",
                  "attributes": {
                    "src": "dut_temp.sv:43.4-207.7"
                  },
                  "parameters": {
                    "A_SIGNED": "00000000000000000000000000000000",
                    "A_WIDTH": "00000000000000000000000000000001",
                    "B_SIGNED": "00000000000000000000000000000000",
                    "B_WIDTH": "00000000000000000000000000000001",
                    "Y_WIDTH": "00000000000000000000000000000001"
                  }
                },
                {
                  "name": "$auto$proc_dlatch.cc:262:make_hold$601",
                  "attributes": {
                    "src": "dut_temp.sv:43.4-207.7"
                  },
                  "parameters": {
                    "A_SIGNED": "00000000000000000000000000000000",
                    "A_WIDTH": "00000000000000000000000000000001",
                    "B_SIGNED": "00000000000000000000000000000000",
                    "B_WIDTH": "00000000000000000000000000000001",
                    "Y_WIDTH": "00000000000000000000000000000001"
                  }
                },
                {
                  "name": "$auto$proc_dlatch.cc:262:make_hold$607",
                  "attributes": {
                    "src": "dut_temp.sv:43.4-207.7"
                  },
                  "parameters": {
                    "A_SIGNED": "00000000000000000000000000000000",
                    "A_WIDTH": "00000000000000000000000000000001",
                    "B_SIGNED": "00000000000000000000000000000000",
                    "B_WIDTH": "00000000000000000000000000000001",
                    "Y_WIDTH": "00000000000000000000000000000001"
                  }
                },
                {
                  "name": "$auto$proc_dlatch.cc:262:make_hold$617",
                  "attributes": {
                    "src": "dut_temp.sv:43.4-207.7"
                  },
                  "parameters": {
                    "A_SIGNED": "00000000000000000000000000000000",
                    "A_WIDTH": "00000000000000000000000000000001",
                    "B_SIGNED": "00000000000000000000000000000000",
                    "B_WIDTH": "00000000000000000000000000000001",
                    "Y_WIDTH": "00000000000000000000000000000001"
                  }
                },
                {
                  "name": "$auto$proc_dlatch.cc:262:make_hold$623",
                  "attributes": {
                    "src": "dut_temp.sv:43.4-207.7"
                  },
                  "parameters": {
                    "A_SIGNED": "00000000000000000000000000000000",
                    "A_WIDTH": "00000000000000000000000000000001",
                    "B_SIGNED": "00000000000000000000000000000000",
                    "B_WIDTH": "00000000000000000000000000000001",
                    "Y_WIDTH": "00000000000000000000000000000001"
                  }
                },
                {
                  "name": "$auto$proc_dlatch.cc:262:make_hold$633",
                  "attributes": {
                    "src": "dut_temp.sv:43.4-207.7"
                  },
                  "parameters": {
                    "A_SIGNED": "00000000000000000000000000000000",
                    "A_WIDTH": "00000000000000000000000000000001",
                    "B_SIGNED": "00000000000000000000000000000000",
                    "B_WIDTH": "00000000000000000000000000000001",
                    "Y_WIDTH": "00000000000000000000000000000001"
                  }
                },
                {
                  "name": "$auto$proc_dlatch.cc:262:make_hold$639",
                  "attributes": {
                    "src": "dut_temp.sv:43.4-207.7"
                  },
                  "parameters": {
                    "A_SIGNED": "00000000000000000000000000000000",
                    "A_WIDTH": "00000000000000000000000000000001",
                    "B_SIGNED": "00000000000000000000000000000000",
                    "B_WIDTH": "00000000000000000000000000000001",
                    "Y_WIDTH": "00000000000000000000000000000001"
                  }
                },
                {
                  "name": "$auto$proc_dlatch.cc:262:make_hold$649",
                  "attributes": {
                    "src": "dut_temp.sv:43.4-207.7"
                  },
                  "parameters": {
                    "A_SIGNED": "00000000000000000000000000000000",
                    "A_WIDTH": "00000000000000000000000000000001",
                    "B_SIGNED": "00000000000000000000000000000000",
                    "B_WIDTH": "00000000000000000000000000000001",
                    "Y_WIDTH": "00000000000000000000000000000001"
                  }
                },
                {
                  "name": "$auto$proc_dlatch.cc:262:make_hold$655",
                  "attributes": {
                    "src": "dut_temp.sv:43.4-207.7"
                  },
                  "parameters": {
                    "A_SIGNED": "00000000000000000000000000000000",
                    "A_WIDTH": "00000000000000000000000000000001",
                    "B_SIGNED": "00000000000000000000000000000000",
                    "B_WIDTH": "00000000000000000000000000000001",
                    "Y_WIDTH": "00000000000000000000000000000001"
                  }
                },
                {
                  "name": "$auto$proc_dlatch.cc:262:make_hold$665",
                  "attributes": {
                    "src": "dut_temp.sv:43.4-207.7"
                  },
                  "parameters": {
                    "A_SIGNED": "00000000000000000000000000000000",
                    "A_WIDTH": "00000000000000000000000000000001",
                    "B_SIGNED": "00000000000000000000000000000000",
                    "B_WIDTH": "00000000000000000000000000000001",
                    "Y_WIDTH": "00000000000000000000000000000001"
                  }
                },
                {
                  "name": "$auto$proc_dlatch.cc:262:make_hold$671",
                  "attributes": {
                    "src": "dut_temp.sv:43.4-207.7"
                  },
                  "parameters": {
                    "A_SIGNED": "00000000000000000000000000000000",
                    "A_WIDTH": "00000000000000000000000000000001",
                    "B_SIGNED": "00000000000000000000000000000000",
                    "B_WIDTH": "00000000000000000000000000000001",
                    "Y_WIDTH": "00000000000000000000000000000001"
                  }
                },
                {
                  "name": "$auto$proc_dlatch.cc:262:make_hold$681",
                  "attributes": {
                    "src": "dut_temp.sv:43.4-207.7"
                  },
                  "parameters": {
                    "A_SIGNED": "00000000000000000000000000000000",
                    "A_WIDTH": "00000000000000000000000000000001",
                    "B_SIGNED": "00000000000000000000000000000000",
                    "B_WIDTH": "00000000000000000000000000000001",
                    "Y_WIDTH": "00000000000000000000000000000001"
                  }
                },
                {
                  "name": "$auto$proc_dlatch.cc:262:make_hold$687",
                  "attributes": {
                    "src": "dut_temp.sv:43.4-207.7"
                  },
                  "parameters": {
                    "A_SIGNED": "00000000000000000000000000000000",
                    "A_WIDTH": "00000000000000000000000000000001",
                    "B_SIGNED": "00000000000000000000000000000000",
                    "B_WIDTH": "00000000000000000000000000000001",
                    "Y_WIDTH": "00000000000000000000000000000001"
                  }
                },
                {
                  "name": "$auto$proc_dlatch.cc:262:make_hold$697",
                  "attributes": {
                    "src": "dut_temp.sv:43.4-207.7"
                  },
                  "parameters": {
                    "A_SIGNED": "00000000000000000000000000000000",
                    "A_WIDTH": "00000000000000000000000000000001",
                    "B_SIGNED": "00000000000000000000000000000000",
                    "B_WIDTH": "00000000000000000000000000000001",
                    "Y_WIDTH": "00000000000000000000000000000001"
                  }
                },
                {
                  "name": "$auto$proc_dlatch.cc:262:make_hold$703",
                  "attributes": {
                    "src": "dut_temp.sv:43.4-207.7"
                  },
                  "parameters": {
                    "A_SIGNED": "00000000000000000000000000000000",
                    "A_WIDTH": "00000000000000000000000000000001",
                    "B_SIGNED": "00000000000000000000000000000000",
                    "B_WIDTH": "00000000000000000000000000000001",
                    "Y_WIDTH": "00000000000000000000000000000001"
                  }
                }
            ]
          },
          {
            "type": "$dlatch",
            "ports": [
                {
                  "name": "D",
                  "direction": "io",
                  "range": [0, 0]
                },
                {
                  "name": "EN",
                  "direction": "io",
                  "range": [0, 0]
                },
                {
                  "name": "Q",
                  "direction": "",
                  "range": [0, 0]
                }
            ],
            "cells": [
                {
                  "name": "$auto$proc_dlatch.cc:432:proc_dlatch$575",
                  "attributes": {
                    "src": "dut_temp.sv:43.4-207.7"
                  },
                  "parameters": {
                    "EN_POLARITY": "00000000000000000000000000000000",
                    "WIDTH": "00000000000000000000000000000001"
                  }
                }
            ]
          },
          {
            "type": "$reduce_or",
            "ports": [
                {
                  "name": "A",
                  "direction": "io",
                  "range": [8, 0]
                },
                {
                  "name": "Y",
                  "direction": "",
                  "range": [0, 0]
                }
            ],
            "cells": [
                {
                  "name": "$auto$opt_reduce.cc:131:opt_pmux$748",
                  "attributes": {

                  },
                  "parameters": {
                    "A_SIGNED": "00000000000000000000000000000000",
                    "A_WIDTH": "00000000000000000000000000001000",
                    "Y_WIDTH": "00000000000000000000000000000001"
                  }
                },
                {
                  "name": "$auto$proc_dlatch.cc:258:make_hold$705",
                  "attributes": {
                    "src": "dut_temp.sv:43.4-207.7"
                  },
                  "parameters": {
                    "A_SIGNED": "00000000000000000000000000000000",
                    "A_WIDTH": "00000000000000000000000000001000",
                    "Y_WIDTH": "00000000000000000000000000000001"
                  }
                }
            ]
          },
          {
            "type": "$add",
            "ports": [
                {
                  "name": "A",
                  "direction": "io",
                  "range": [2, 0]
                },
                {
                  "name": "B",
                  "direction": "io",
                  "range": [0, 0]
                },
                {
                  "name": "Y",
                  "direction": "",
                  "range": [2, 0]
                }
            ],
            "cells": [
                {
                  "name": "$add$dut_temp.sv:216$50",
                  "attributes": {
                    "src": "dut_temp.sv:216.66-216.83"
                  },
                  "parameters": {
                    "A_SIGNED": "00000000000000000000000000000000",
                    "A_WIDTH": "00000000000000000000000000000010",
                    "B_SIGNED": "00000000000000000000000000000000",
                    "B_WIDTH": "00000000000000000000000000000001",
                    "Y_WIDTH": "00000000000000000000000000000010"
                  }
                }
            ]
          }
        ],
        "attributes": {
            "keep": "00000000000000000000000000000001",
            "top": "00000000000000000000000000000001",
            "src": "dut_temp.sv:2.1-291.10"
        }
      }
  ]
}
